oc_validator/__init__.py
oc_validator/csv_wellformedness.py
oc_validator/helper.py
oc_validator/id_existence.py
oc_validator/id_syntax.py
oc_validator/id_type_alignment.json
oc_validator/interface/__init__.py
oc_validator/interface/gui.py
oc_validator/interface/invalid-template.html
oc_validator/interface/README.md
oc_validator/interface/run_gui.py
oc_validator/interface/script.js
oc_validator/interface/style.css
oc_validator/interface/valid_template.html
oc_validator/main.py
oc_validator/messages.yaml
oc_validator/semantics.py
oc_validator-0.3.13.dist-info/METADATA
oc_validator-0.3.13.dist-info/WHEEL
oc_validator-0.3.13.dist-info/RECORD
