Metadata-Version: 2.1
Name: oc-validator
Version: 0.3.13
Summary: A software to validate CSV documents storing citation data and bibliographic metadata according to the OpenCitations Data Model.
Author: Elia Rizzetto
Author-email: elia.rizzetto@gmail.com
Requires-Python: >=3.9,<4.0
Classifier: Programming Language :: Python :: 3
Classifier: Programming Language :: Python :: 3.9
Classifier: Programming Language :: Python :: 3.10
Classifier: Programming Language :: Python :: 3.11
Classifier: Programming Language :: Python :: 3.12
Requires-Dist: beautifulsoup4 (>=4.12.3,<5.0.0)
Requires-Dist: jinja2 (>=3.1.4,<4.0.0)
Requires-Dist: oc-ds-converter (>=1.0.4,<2.0.0) ; python_version >= "3.9" and python_version < "3.14"
Requires-Dist: pyyaml (>=6.0,<7.0)
Requires-Dist: roman (>=4.0,<5.0)
Requires-Dist: sparqlwrapper (>=2.0.0,<3.0.0)
